MANIFEST.in
setup.py
PyBioMaps.egg-info/PKG-INFO
PyBioMaps.egg-info/SOURCES.txt
PyBioMaps.egg-info/dependency_links.txt
PyBioMaps.egg-info/not-zip-safe
PyBioMaps.egg-info/requires.txt
PyBioMaps.egg-info/top_level.txt
pybiomaps/__init__.py
pybiomaps/server.py
pybiomaps/plugins/__init__.py
pybiomaps/plugins/level.py
pybiomaps/plugins/newick.py
pybiomaps/plugins/phb.py
pybiomaps/plugins/ruler.py
pybiomaps/plugins/seq.py
pybiomaps/render/__init__.py
pybiomaps/render/color.py
pybiomaps/render/geometry.py
pybiomaps/resource/__init__.py
pybiomaps/resource/common.py
pybiomaps/static/bg.png
pybiomaps/static/favicon.ico
pybiomaps/static/css/lucullus.css
pybiomaps/static/css/main.css
pybiomaps/static/img/joystick.png
pybiomaps/static/img/joystick.svg
pybiomaps/static/img/logo.png
pybiomaps/static/img/mark.png
pybiomaps/static/img/progressbar.gif
pybiomaps/static/img/icons/AUTHORS
pybiomaps/static/img/icons/COPYING
pybiomaps/static/img/icons/README
pybiomaps/static/img/icons/16x16/Makefile.am
pybiomaps/static/img/icons/16x16/Makefile.in
pybiomaps/static/img/icons/16x16/actions/Makefile.am
pybiomaps/static/img/icons/16x16/actions/Makefile.in
pybiomaps/static/img/icons/16x16/actions/address-book-new.png
pybiomaps/static/img/icons/16x16/actions/application-exit.png
pybiomaps/static/img/icons/16x16/actions/appointment-new.png
pybiomaps/static/img/icons/16x16/actions/bookmark-new.png
pybiomaps/static/img/icons/16x16/actions/contact-new.png
pybiomaps/static/img/icons/16x16/actions/document-new.png
pybiomaps/static/img/icons/16x16/actions/document-open-recent.png
pybiomaps/static/img/icons/16x16/actions/document-open.png
pybiomaps/static/img/icons/16x16/actions/document-page-setup.png
pybiomaps/static/img/icons/16x16/actions/document-print-preview.png
pybiomaps/static/img/icons/16x16/actions/document-print.png
pybiomaps/static/img/icons/16x16/actions/document-properties.png
pybiomaps/static/img/icons/16x16/actions/document-revert.png
pybiomaps/static/img/icons/16x16/actions/document-save-as.png
pybiomaps/static/img/icons/16x16/actions/document-save.png
pybiomaps/static/img/icons/16x16/actions/document-send.png
pybiomaps/static/img/icons/16x16/actions/edit-clear.png
